{
  "data": [
    {
      "id": "G40",
      "nameRus": "Гаражный массив",
      "nameKaz": "Гараждық алабы"
    },
    {
      "id": "G42",
      "nameRus": "Садовое общество",
      "nameKaz": "Бау-бақшалық қоғамы"
    },
    {
      "id": "G41",
      "nameRus": "Станция",
      "nameKaz": "Станциясы"
    },
    {
      "id": "G44",
      "nameRus": "Отделение",
      "nameKaz": "Бөлімшесі"
    },
    {
      "id": "G43",
      "nameRus": "База отдыха",
      "nameKaz": "Демалыс базасы"
    },
    {
      "id": "G46",
      "nameRus": "Жилой массив",
      "nameKaz": "Тұрғын үй алабы"
    },
    {
      "id": "G48",
      "nameRus": "Участок",
      "nameKaz": "Телімі"
    },
    {
      "id": "G47",
      "nameRus": "Площадка",
      "nameKaz": "Алаңқайы"
    },
    {
      "id": "A1",
      "nameRus": "Село",
      "nameKaz": "ауылы"
    },
    {
      "id": "A2",
      "nameRus": "Поселок",
      "nameKaz": "кенті"
    },
    {
      "id": "A3",
      "nameRus": "Сельский округ",
      "nameKaz": "ауылдық округі"
    },
    {
      "id": "A4",
      "nameRus": "Город районного значения",
      "nameKaz": "аудандық маңызы бар қаласы"
    },
    {
      "id": "A5",
      "nameRus": "Район",
      "nameKaz": "ауданы"
    },
    {
      "id": "A6",
      "nameRus": "Город областного значения",
      "nameKaz": "облыстық маңызы бар қаласы"
    },
    {
      "id": "A7",
      "nameRus": "Область",
      "nameKaz": "облысы"
    },
    {
      "id": "A8",
      "nameRus": "Район в городе",
      "nameKaz": "қала ішіндегі аудан"
    },
    {
      "id": "A9",
      "nameRus": "Город республиканского значения",
      "nameKaz": "республикалық маңызы бар қаласы"
    },
    {
      "id": "A10",
      "nameRus": "Республика",
      "nameKaz": "Республикасы"
    },
    {
      "id": "A11",
      "nameRus": "Сельский совет",
      "nameKaz": "Сельский совет"
    },
    {
      "id": "G51",
      "nameRus": "Крестьянское хозяйство",
      "nameKaz": "Шаруа қожалығы"
    },
    {
      "id": "G50",
      "nameRus": "Промышленная зона",
      "nameKaz": "Өнеркәсіптік аймақ"
    },
    {
      "id": "G166",
      "nameRus": "местность",
      "nameKaz": "жері"
    },
    {
      "id": "G58",
      "nameRus": "Садоводческий коллектив",
      "nameKaz": "Бағбандық ұжым"
    },
    {
      "id": "B1",
      "nameRus": "строение",
      "nameKaz": "құрылыс"
    },
    {
      "id": "B2",
      "nameRus": "дом",
      "nameKaz": "үй"
    },
    {
      "id": "B3",
      "nameRus": "сооружение",
      "nameKaz": "құрылым"
    },
    {
      "id": "B4",
      "nameRus": "гараж",
      "nameKaz": "көлікжай"
    },
    {
      "id": "B5",
      "nameRus": "здание",
      "nameKaz": "ғимарат"
    },
    {
      "id": "B6",
      "nameRus": "бокс",
      "nameKaz": "бокс"
    },
    {
      "id": "B7",
      "nameRus": "дача",
      "nameKaz": "саяжай"
    },
    {
      "id": "B8",
      "nameRus": "участок",
      "nameKaz": "телім"
    },
    {
      "id": "G62",
      "nameRus": "Потребительский кооператив",
      "nameKaz": "Тұтыну кооперативі"
    },
    {
      "id": "G61",
      "nameRus": "Потребительский кооператив собственников гаражей",
      "nameKaz": "Гараж иелерінің тұтыну кооперативі"
    },
    {
      "id": "G64",
      "nameRus": "Дачный массив",
      "nameKaz": "Саяжай алабы"
    },
    {
      "id": "G63",
      "nameRus": "Садоводческое товарищество",
      "nameKaz": "Бағбандық серіктестік"
    },
    {
      "id": "G66",
      "nameRus": "Урочище",
      "nameKaz": "Коныс"
    },
    {
      "id": "G110",
      "nameRus": "Жилой район",
      "nameKaz": "Тұрғын аудан"
    },
    {
      "id": "G68",
      "nameRus": "Территория",
      "nameKaz": "Аумақ"
    },
    {
      "id": "G67",
      "nameRus": "Зона",
      "nameKaz": "Аймақ"
    },
    {
      "id": "G112",
      "nameRus": "Блок",
      "nameKaz": "Блок"
    },
    {
      "id": "G111",
      "nameRus": "Потребительский кооператив собственников садовых, дачных участков",
      "nameKaz": "Бау-бақша, саяжай учаскелер меншік иелерінің тұтыну кооперативі"
    },
    {
      "id": "G114",
      "nameRus": "Имущественный комплекс",
      "nameKaz": "Мүліктік кешені"
    },
    {
      "id": "G113",
      "nameRus": "военный городок",
      "nameKaz": "Әскери қалашық"
    },
    {
      "id": "G115",
      "nameRus": "Оздоровительный комплекс",
      "nameKaz": "Сауықтыру кешені"
    },
    {
      "id": "G71",
      "nameRus": "Потребительский гаражный кооператив",
      "nameKaz": "Гараж тұтыну кооперативі"
    },
    {
      "id": "G73",
      "nameRus": "Разрез",
      "nameKaz": "Қиық"
    },
    {
      "id": "G72",
      "nameRus": "Потребительский кооператив собственников дачных участков",
      "nameKaz": "Саяжайлық жер телімдері меншік иелері тұтыну кооперативі"
    },
    {
      "id": "G75",
      "nameRus": "Дачный комплекс",
      "nameKaz": "Саяжай кешені"
    },
    {
      "id": "A37",
      "nameRus": "РАЗЪЕЗД",
      "nameKaz": "ЖОЛ АЙРЫҒЫ"
    },
    {
      "id": "G74",
      "nameRus": "Садоводческое общество",
      "nameKaz": "Бағбаншылық қоғамы"
    },
    {
      "id": "A38",
      "nameRus": "Станция",
      "nameKaz": "Станциясы"
    },
    {
      "id": "G77",
      "nameRus": "Учетный квартал",
      "nameKaz": "Есептік квартал"
    },
    {
      "id": "G76",
      "nameRus": "Потребительский кооператив садоводов",
      "nameKaz": "Бау-бақша тұтыну кооперативі"
    },
    {
      "id": "G79",
      "nameRus": "Гаражно-Эксплуатационный кооператив",
      "nameKaz": "Гараж Пайдаланушылар кооперативі"
    },
    {
      "id": "G78",
      "nameRus": "Гаражно-Строительный кооператив",
      "nameKaz": "Гараж- Құрылыс кооперативі"
    },
    {
      "id": "G100",
      "nameRus": "Полевой стан",
      "nameKaz": "Егіс алаңы"
    },
    {
      "id": "G103",
      "nameRus": "Комплекс",
      "nameKaz": "Кешен"
    },
    {
      "id": "G105",
      "nameRus": "Центр отдыха",
      "nameKaz": "Демалыс орталығы"
    },
    {
      "id": "G104",
      "nameRus": "Рыбопитомник",
      "nameKaz": "Балық питомнигі"
    },
    {
      "id": "G107",
      "nameRus": "Потребительский дачный кооператив",
      "nameKaz": "Тұтыну саяжай кооперативі"
    },
    {
      "id": "G106",
      "nameRus": "Простое садоводческое товарищество",
      "nameKaz": "Қарапайым бағбаншылық серіктестігі"
    },
    {
      "id": "G109",
      "nameRus": "Дом отдыха",
      "nameKaz": "Демалыс үйі"
    },
    {
      "id": "G108",
      "nameRus": "Потребительский кооператив Cадоводческое общество",
      "nameKaz": "Бағаншылық қоғамы тұтыну кооперативі"
    },
    {
      "id": "G80",
      "nameRus": "Кадастровый квартал",
      "nameKaz": "Кадастр кварталы"
    },
    {
      "id": "G82",
      "nameRus": "Потребительский кооператив садоводческих товариществ",
      "nameKaz": "Бау-бақша серіктестіктерінің кооперативі"
    },
    {
      "id": "G81",
      "nameRus": "Садоводческо-потребительский кооператив",
      "nameKaz": "Бау-бақша тұтынушылар кооперативі"
    },
    {
      "id": "A45",
      "nameRus": "НАСЕЛЕННЫЙ ПУНКТ",
      "nameKaz": "ЕЛДІ МЕКЕНІ"
    },
    {
      "id": "G84",
      "nameRus": "Ряд",
      "nameKaz": "Қатар"
    },
    {
      "id": "G83",
      "nameRus": "Общество садоводов",
      "nameKaz": "Бау-бақша қоғамы"
    },
    {
      "id": "G86",
      "nameRus": "поселок",
      "nameKaz": "кент"
    },
    {
      "id": "G85",
      "nameRus": "Потребительский Kооператив Садоводческое Общество",
      "nameKaz": "Бағбандық Қоғам Тұтыну Кооперативі"
    },
    {
      "id": "A49",
      "nameRus": "ЛЕСХОЗ",
      "nameKaz": "ОРМАН ШАРУАШЫЛЫҒЫ"
    },
    {
      "id": "G88",
      "nameRus": "Ферма",
      "nameKaz": "Ферма"
    },
    {
      "id": "G87",
      "nameRus": "ПРОИЗВОДСТВЕННЫЙ КООПЕРАТИВ",
      "nameKaz": "ӨНДІРІСТІК КООПЕРАТИВІ"
    },
    {
      "id": "G89",
      "nameRus": "Таможенный пост",
      "nameKaz": "Кеден бекеті"
    },
    {
      "id": "A52",
      "nameRus": "ПОСЕЛКОВЫЙ ОКРУГ",
      "nameKaz": "КЕНТТІК ОКРУГІ"
    },
    {
      "id": "G91",
      "nameRus": "Кардон",
      "nameKaz": "Кардон"
    },
    {
      "id": "A53",
      "nameRus": "ЗАИМКА",
      "nameKaz": "ЗАИМКА"
    },
    {
      "id": "G90",
      "nameRus": "Лесничество",
      "nameKaz": "Орман шаруашылығы"
    },
    {
      "id": "A54",
      "nameRus": "ЗИМОВКА",
      "nameKaz": "ҚЫСТАУЫ"
    },
    {
      "id": "G93",
      "nameRus": "Садоводческий комплекс",
      "nameKaz": "Бағбандық кешені"
    },
    {
      "id": "A55",
      "nameRus": "УЧАСТОК",
      "nameKaz": "УЧАСТІГІ "
    },
    {
      "id": "G92",
      "nameRus": "Потребительский кооператив собственников индивидуальных гаражей",
      "nameKaz": "Жеке гараж иелерінің тұтыну кооперативі"
    },
    {
      "id": "A56",
      "nameRus": "ОТДЕЛЕНИЕ",
      "nameKaz": "БӨЛІМШЕСІ"
    },
    {
      "id": "G95",
      "nameRus": "Имущественный комплекс",
      "nameKaz": "Мүліктік кешені"
    },
    {
      "id": "A57",
      "nameRus": "ЗАСТАВА",
      "nameKaz": "ШЕКАРАЛЫҚ БЕКЕТ"
    },
    {
      "id": "G94",
      "nameRus": "Полевой стан",
      "nameKaz": "Егіс алаңы"
    },
    {
      "id": "G97",
      "nameRus": "Комплекс",
      "nameKaz": "Кешен"
    },
    {
      "id": "A59",
      "nameRus": "СЕЛЬСКИЙ ОКРУГ",
      "nameKaz": "АУЫЛДЫҚ ОКРУГІ"
    },
    {
      "id": "G96",
      "nameRus": "Оздоровительный комплекс",
      "nameKaz": "Сауықтыру кешені"
    },
    {
      "id": "G11",
      "nameRus": "улица",
      "nameKaz": "көшесі"
    },
    {
      "id": "G13",
      "nameRus": "Аллея",
      "nameKaz": "Аллеясы"
    },
    {
      "id": "G12",
      "nameRus": "Бульвар",
      "nameKaz": "Бульвары"
    },
    {
      "id": "G15",
      "nameRus": "Проспект",
      "nameKaz": "Даңғылы"
    },
    {
      "id": "G14",
      "nameRus": "Площадь",
      "nameKaz": "Алаңы"
    },
    {
      "id": "G17",
      "nameRus": "Дорога",
      "nameKaz": "Жолы"
    },
    {
      "id": "G16",
      "nameRus": "Линия",
      "nameKaz": "Желісі"
    },
    {
      "id": "G19",
      "nameRus": "Переулок",
      "nameKaz": "Тұйық көше"
    },
    {
      "id": "G18",
      "nameRus": "Набережная",
      "nameKaz": "Жағалауы"
    },
    {
      "id": "A65",
      "nameRus": "ФЕРМА",
      "nameKaz": "ФЕРМАСЫ"
    },
    {
      "id": "A66",
      "nameRus": "Разъезд",
      "nameKaz": "Разъезд"
    },
    {
      "id": "A69",
      "nameRus": "ПОДХОЗ",
      "nameKaz": "ҚОСАЛҚЫ ШАРУАШЫЛЫҚ"
    },
    {
      "id": "G20",
      "nameRus": "Проезд",
      "nameKaz": "Өтпе жолы"
    },
    {
      "id": "G22",
      "nameRus": "Заимка",
      "nameKaz": "Займкасы"
    },
    {
      "id": "G21",
      "nameRus": "Лесхоз",
      "nameKaz": "Орманшары"
    },
    {
      "id": "G24",
      "nameRus": "Микрорайон",
      "nameKaz": "Шағын ауданы"
    },
    {
      "id": "G23",
      "nameRus": "Зимовка",
      "nameKaz": "Қыстауы"
    },
    {
      "id": "G26",
      "nameRus": "Застава",
      "nameKaz": "Шекара бекеті"
    },
    {
      "id": "G25",
      "nameRus": "квартал",
      "nameKaz": "орам"
    },
    {
      "id": "G28",
      "nameRus": "Тупик",
      "nameKaz": "Тұйық көшесі"
    },
    {
      "id": "G27",
      "nameRus": "Шоссе",
      "nameKaz": "Шоссесы"
    },
    {
      "id": "G29",
      "nameRus": "Тракт",
      "nameKaz": "Даңғыл жолы"
    },
    {
      "id": "A70",
      "nameRus": "САНАТОРИЙ",
      "nameKaz": "ШИПАЖАЙ"
    },
    {
      "id": "G31",
      "nameRus": "Разъезд",
      "nameKaz": "Жол айрығы"
    },
    {
      "id": "G30",
      "nameRus": "Воинская часть",
      "nameKaz": "Әскери бөлімі"
    },
    {
      "id": "G33",
      "nameRus": "Гаражный кооператив",
      "nameKaz": "Гараждық кооперативі"
    },
    {
      "id": "G32",
      "nameRus": "Дачный кооператив",
      "nameKaz": "Cаяжай кооперативі"
    },
    {
      "id": "G35",
      "nameRus": "Гаражное общество",
      "nameKaz": "Гараждық қоғамы"
    },
    {
      "id": "G34",
      "nameRus": "Массив",
      "nameKaz": "Алабы"
    },
    {
      "id": "G36",
      "nameRus": "Дачное общество",
      "nameKaz": "Саяжай қоғамы"
    },
    {
      "id": "G39",
      "nameRus": "Трасса",
      "nameKaz": "Тас жолы"
    }
  ],
  "total": 121,
  "from": 0
}
